milvus/__init__.py
milvus/settings.py
milvus/utils.py
milvus/client/__init__.py
milvus/client/abs_client.py
milvus/client/abstract.py
milvus/client/asynch.py
milvus/client/blob.py
milvus/client/check.py
milvus/client/client_hooks.py
milvus/client/exceptions.py
milvus/client/grpc_handler.py
milvus/client/http_handler.py
milvus/client/pool.py
milvus/client/prepare.py
milvus/client/stub.py
milvus/client/types.py
milvus/client/utils.py
milvus/client/hooks/__init__.py
milvus/client/hooks/abstract.py
milvus/grpc_gen/__init__.py
milvus/grpc_gen/common_pb2.py
milvus/grpc_gen/milvus_pb2.py
milvus/grpc_gen/milvus_pb2_grpc.py
milvus/grpc_gen/schema_pb2.py
tests/__init__.py
tests/conftest.py
tests/constants.py
tests/factorys.py
tests/test_bulk_insert.py
tests/test_create_collection.py
tests/test_drop_collection.py
tests/test_get_collection_info.py
tests/test_has_collection.py
tests/test_insert.py
tests/test_list_collections.py
tests/test_load_collection.py
tests/test_load_partitions.py
tests/test_partition.py
tests/test_search.py
tests/utils.py
pymilvus_distributed-0.0.66.dist-info/LICENSE
pymilvus_distributed-0.0.66.dist-info/METADATA
pymilvus_distributed-0.0.66.dist-info/WHEEL
pymilvus_distributed-0.0.66.dist-info/top_level.txt
pymilvus_distributed-0.0.66.dist-info/RECORD
